{
  "frames": {
    "Elven-Attack-Up-10.png": {
      "frame": {
        "x": 1,
        "y": 1,
        "w": 26,
        "h": 60
      },
      "rotated": false,
      "trimmed": true,
      "spriteSourceSize": {
        "x": 18,
        "y": 4,
        "w": 26,
        "h": 60
      },
      "sourceSize": {
        "w": 64,
        "h": 64
      },
      "pivot": {
        "x": 0.5,
        "y": 0.5
      }
    },
    "Elven-Attack-Up-09.png": {
      "frame": {
        "x": 29,
        "y": 1,
        "w": 29,
        "h": 60
      },
      "rotated": false,
      "trimmed": true,
      "spriteSourceSize": {
        "x": 18,
        "y": 4,
        "w": 29,
        "h": 60
      },
      "sourceSize": {
        "w": 64,
        "h": 64
      },
      "pivot": {
        "x": 0.5,
        "y": 0.5
      }
    },
    "Elven-Attack-Up-07.png": {
      "frame": {
        "x": 60,
        "y": 1,
        "w": 29,
        "h": 60
      },
      "rotated": false,
      "trimmed": true,
      "spriteSourceSize": {
        "x": 18,
        "y": 4,
        "w": 29,
        "h": 60
      },
      "sourceSize": {
        "w": 64,
        "h": 64
      },
      "pivot": {
        "x": 0.5,
        "y": 0.5
      }
    },
    "Elven-Attack-Up-06.png": {
      "frame": {
        "x": 1,
        "y": 63,
        "w": 28,
        "h": 59
      },
      "rotated": false,
      "trimmed": true,
      "spriteSourceSize": {
        "x": 18,
        "y": 5,
        "w": 28,
        "h": 59
      },
      "sourceSize": {
        "w": 64,
        "h": 64
      },
      "pivot": {
        "x": 0.5,
        "y": 0.5
      }
    },
    "Elven-Attack-Up-05.png": {
      "frame": {
        "x": 31,
        "y": 63,
        "w": 27,
        "h": 58
      },
      "rotated": false,
      "trimmed": true,
      "spriteSourceSize": {
        "x": 18,
        "y": 6,
        "w": 27,
        "h": 58
      },
      "sourceSize": {
        "w": 64,
        "h": 64
      },
      "pivot": {
        "x": 0.5,
        "y": 0.5
      }
    },
    "Elven-Attack-Up-08.png": {
      "frame": {
        "x": 91,
        "y": 1,
        "w": 30,
        "h": 57
      },
      "rotated": false,
      "trimmed": true,
      "spriteSourceSize": {
        "x": 18,
        "y": 7,
        "w": 30,
        "h": 57
      },
      "sourceSize": {
        "w": 64,
        "h": 64
      },
      "pivot": {
        "x": 0.5,
        "y": 0.5
      }
    },
    "Elven-Attack-Left-06.png": {
      "frame": {
        "x": 60,
        "y": 63,
        "w": 44,
        "h": 56
      },
      "rotated": false,
      "trimmed": true,
      "spriteSourceSize": {
        "x": 1,
        "y": 7,
        "w": 44,
        "h": 56
      },
      "sourceSize": {
        "w": 64,
        "h": 64
      },
      "pivot": {
        "x": 0.5,
        "y": 0.5
      }
    },
    "Elven-Attack-Right-06.png": {
      "frame": {
        "x": 123,
        "y": 1,
        "w": 45,
        "h": 56
      },
      "rotated": false,
      "trimmed": true,
      "spriteSourceSize": {
        "x": 18,
        "y": 7,
        "w": 45,
        "h": 56
      },
      "sourceSize": {
        "w": 64,
        "h": 64
      },
      "pivot": {
        "x": 0.5,
        "y": 0.5
      }
    },
    "Elven-Attack-Up-04.png": {
      "frame": {
        "x": 106,
        "y": 60,
        "w": 29,
        "h": 55
      },
      "rotated": false,
      "trimmed": true,
      "spriteSourceSize": {
        "x": 18,
        "y": 9,
        "w": 29,
        "h": 55
      },
      "sourceSize": {
        "w": 64,
        "h": 64
      },
      "pivot": {
        "x": 0.5,
        "y": 0.5
      }
    },
    "Elven-Attack-Right-05.png": {
      "frame": {
        "x": 1,
        "y": 124,
        "w": 45,
        "h": 54
      },
      "rotated": false,
      "trimmed": true,
      "spriteSourceSize": {
        "x": 19,
        "y": 9,
        "w": 45,
        "h": 54
      },
      "sourceSize": {
        "w": 64,
        "h": 64
      },
      "pivot": {
        "x": 0.5,
        "y": 0.5
      }
    },
    "Elven-Attack-Left-05.png": {
      "frame": {
        "x": 48,
        "y": 123,
        "w": 44,
        "h": 54
      },
      "rotated": false,
      "trimmed": true,
      "spriteSourceSize": {
        "x": 0,
        "y": 9,
        "w": 44,
        "h": 54
      },
      "sourceSize": {
        "w": 64,
        "h": 64
      },
      "pivot": {
        "x": 0.5,
        "y": 0.5
      }
    },
    "Elven-Attack-Right-07.png": {
      "frame": {
        "x": 94,
        "y": 121,
        "w": 45,
        "h": 54
      },
      "rotated": false,
      "trimmed": true,
      "spriteSourceSize": {
        "x": 15,
        "y": 9,
        "w": 45,
        "h": 54
      },
      "sourceSize": {
        "w": 64,
        "h": 64
      },
      "pivot": {
        "x": 0.5,
        "y": 0.5
      }
    },
    "Elven-Attack-Left-07.png": {
      "frame": {
        "x": 170,
        "y": 1,
        "w": 44,
        "h": 54
      },
      "rotated": false,
      "trimmed": true,
      "spriteSourceSize": {
        "x": 4,
        "y": 9,
        "w": 44,
        "h": 54
      },
      "sourceSize": {
        "w": 64,
        "h": 64
      },
      "pivot": {
        "x": 0.5,
        "y": 0.5
      }
    },
    "Elven-Attack-Up-03.png": {
      "frame": {
        "x": 137,
        "y": 59,
        "w": 26,
        "h": 52
      },
      "rotated": false,
      "trimmed": true,
      "spriteSourceSize": {
        "x": 18,
        "y": 12,
        "w": 26,
        "h": 52
      },
      "sourceSize": {
        "w": 64,
        "h": 64
      },
      "pivot": {
        "x": 0.5,
        "y": 0.5
      }
    },
    "Elven-Attack-Right-10.png": {
      "frame": {
        "x": 170,
        "y": 57,
        "w": 34,
        "h": 52
      },
      "rotated": false,
      "trimmed": true,
      "spriteSourceSize": {
        "x": 17,
        "y": 11,
        "w": 34,
        "h": 52
      },
      "sourceSize": {
        "w": 64,
        "h": 64
      },
      "pivot": {
        "x": 0.5,
        "y": 0.5
      }
    },
    "Elven-Attack-Right-09.png": {
      "frame": {
        "x": 141,
        "y": 113,
        "w": 35,
        "h": 52
      },
      "rotated": false,
      "trimmed": true,
      "spriteSourceSize": {
        "x": 16,
        "y": 11,
        "w": 35,
        "h": 52
      },
      "sourceSize": {
        "w": 64,
        "h": 64
      },
      "pivot": {
        "x": 0.5,
        "y": 0.5
      }
    },
    "Elven-Attack-Left-10.png": {
      "frame": {
        "x": 178,
        "y": 111,
        "w": 34,
        "h": 52
      },
      "rotated": false,
      "trimmed": true,
      "spriteSourceSize": {
        "x": 12,
        "y": 11,
        "w": 34,
        "h": 52
      },
      "sourceSize": {
        "w": 64,
        "h": 64
      },
      "pivot": {
        "x": 0.5,
        "y": 0.5
      }
    },
    "Elven-Attack-Left-09.png": {
      "frame": {
        "x": 1,
        "y": 180,
        "w": 35,
        "h": 52
      },
      "rotated": false,
      "trimmed": true,
      "spriteSourceSize": {
        "x": 12,
        "y": 11,
        "w": 35,
        "h": 52
      },
      "sourceSize": {
        "w": 64,
        "h": 64
      },
      "pivot": {
        "x": 0.5,
        "y": 0.5
      }
    },
    "Elven-Walk-Left-5.png": {
      "frame": {
        "x": 38,
        "y": 180,
        "w": 27,
        "h": 52
      },
      "rotated": false,
      "trimmed": true,
      "spriteSourceSize": {
        "x": 20,
        "y": 12,
        "w": 27,
        "h": 52
      },
      "sourceSize": {
        "w": 64,
        "h": 64
      },
      "pivot": {
        "x": 0.5,
        "y": 0.5
      }
    },
    "Elven-Walk-Left-6.png": {
      "frame": {
        "x": 67,
        "y": 179,
        "w": 26,
        "h": 52
      },
      "rotated": false,
      "trimmed": true,
      "spriteSourceSize": {
        "x": 20,
        "y": 12,
        "w": 26,
        "h": 52
      },
      "sourceSize": {
        "w": 64,
        "h": 64
      },
      "pivot": {
        "x": 0.5,
        "y": 0.5
      }
    },
    "Elven-Attack-Left-04.png": {
      "frame": {
        "x": 95,
        "y": 177,
        "w": 42,
        "h": 51
      },
      "rotated": false,
      "trimmed": true,
      "spriteSourceSize": {
        "x": 5,
        "y": 12,
        "w": 42,
        "h": 51
      },
      "sourceSize": {
        "w": 64,
        "h": 64
      },
      "pivot": {
        "x": 0.5,
        "y": 0.5
      }
    },
    "Elven-Walk-Right-8.png": {
      "frame": {
        "x": 139,
        "y": 177,
        "w": 24,
        "h": 51
      },
      "rotated": false,
      "trimmed": true,
      "spriteSourceSize": {
        "x": 20,
        "y": 12,
        "w": 24,
        "h": 51
      },
      "sourceSize": {
        "w": 64,
        "h": 64
      },
      "pivot": {
        "x": 0.5,
        "y": 0.5
      }
    },
    "Elven-Walk-Left-1.png": {
      "frame": {
        "x": 178,
        "y": 165,
        "w": 24,
        "h": 51
      },
      "rotated": false,
      "trimmed": true,
      "spriteSourceSize": {
        "x": 20,
        "y": 12,
        "w": 24,
        "h": 51
      },
      "sourceSize": {
        "w": 64,
        "h": 64
      },
      "pivot": {
        "x": 0.5,
        "y": 0.5
      }
    },
    "Elven-Walk-Left-2.png": {
      "frame": {
        "x": 216,
        "y": 1,
        "w": 24,
        "h": 51
      },
      "rotated": false,
      "trimmed": true,
      "spriteSourceSize": {
        "x": 20,
        "y": 12,
        "w": 24,
        "h": 51
      },
      "sourceSize": {
        "w": 64,
        "h": 64
      },
      "pivot": {
        "x": 0.5,
        "y": 0.5
      }
    },
    "Elven-Walk-Left-4.png": {
      "frame": {
        "x": 214,
        "y": 57,
        "w": 26,
        "h": 51
      },
      "rotated": false,
      "trimmed": true,
      "spriteSourceSize": {
        "x": 20,
        "y": 12,
        "w": 26,
        "h": 51
      },
      "sourceSize": {
        "w": 64,
        "h": 64
      },
      "pivot": {
        "x": 0.5,
        "y": 0.5
      }
    },
    "Elven-Walk-Left-8.png": {
      "frame": {
        "x": 214,
        "y": 110,
        "w": 24,
        "h": 51
      },
      "rotated": false,
      "trimmed": true,
      "spriteSourceSize": {
        "x": 20,
        "y": 12,
        "w": 24,
        "h": 51
      },
      "sourceSize": {
        "w": 64,
        "h": 64
      },
      "pivot": {
        "x": 0.5,
        "y": 0.5
      }
    },
    "Elven-Attack-Right-04.png": {
      "frame": {
        "x": 1,
        "y": 234,
        "w": 43,
        "h": 51
      },
      "rotated": false,
      "trimmed": true,
      "spriteSourceSize": {
        "x": 16,
        "y": 12,
        "w": 43,
        "h": 51
      },
      "sourceSize": {
        "w": 64,
        "h": 64
      },
      "pivot": {
        "x": 0.5,
        "y": 0.5
      }
    },
    "Elven-Walk-Left-7.png": {
      "frame": {
        "x": 46,
        "y": 234,
        "w": 24,
        "h": 51
      },
      "rotated": false,
      "trimmed": true,
      "spriteSourceSize": {
        "x": 20,
        "y": 12,
        "w": 24,
        "h": 51
      },
      "sourceSize": {
        "w": 64,
        "h": 64
      },
      "pivot": {
        "x": 0.5,
        "y": 0.5
      }
    },
    "Elven-Walk-Left-0.png": {
      "frame": {
        "x": 72,
        "y": 233,
        "w": 24,
        "h": 51
      },
      "rotated": false,
      "trimmed": true,
      "spriteSourceSize": {
        "x": 19,
        "y": 12,
        "w": 24,
        "h": 51
      },
      "sourceSize": {
        "w": 64,
        "h": 64
      },
      "pivot": {
        "x": 0.5,
        "y": 0.5
      }
    },
    "Elven-Attack-Left-02.png": {
      "frame": {
        "x": 98,
        "y": 230,
        "w": 38,
        "h": 50
      },
      "rotated": false,
      "trimmed": true,
      "spriteSourceSize": {
        "x": 8,
        "y": 13,
        "w": 38,
        "h": 50
      },
      "sourceSize": {
        "w": 64,
        "h": 64
      },
      "pivot": {
        "x": 0.5,
        "y": 0.5
      }
    },
    "Elven-Attack-Right-00.png": {
      "frame": {
        "x": 138,
        "y": 230,
        "w": 44,
        "h": 50
      },
      "rotated": false,
      "trimmed": true,
      "spriteSourceSize": {
        "x": 13,
        "y": 13,
        "w": 44,
        "h": 50
      },
      "sourceSize": {
        "w": 64,
        "h": 64
      },
      "pivot": {
        "x": 0.5,
        "y": 0.5
      }
    },
    "Elven-Attack-Right-01.png": {
      "frame": {
        "x": 184,
        "y": 218,
        "w": 37,
        "h": 50
      },
      "rotated": false,
      "trimmed": true,
      "spriteSourceSize": {
        "x": 15,
        "y": 13,
        "w": 37,
        "h": 50
      },
      "sourceSize": {
        "w": 64,
        "h": 64
      },
      "pivot": {
        "x": 0.5,
        "y": 0.5
      }
    },
    "Elven-Attack-Right-02.png": {
      "frame": {
        "x": 242,
        "y": 1,
        "w": 39,
        "h": 50
      },
      "rotated": false,
      "trimmed": true,
      "spriteSourceSize": {
        "x": 17,
        "y": 13,
        "w": 39,
        "h": 50
      },
      "sourceSize": {
        "w": 64,
        "h": 64
      },
      "pivot": {
        "x": 0.5,
        "y": 0.5
      }
    },
    "Elven-Walk-Right-7.png": {
      "frame": {
        "x": 204,
        "y": 165,
        "w": 24,
        "h": 50
      },
      "rotated": false,
      "trimmed": true,
      "spriteSourceSize": {
        "x": 20,
        "y": 13,
        "w": 24,
        "h": 50
      },
      "sourceSize": {
        "w": 64,
        "h": 64
      },
      "pivot": {
        "x": 0.5,
        "y": 0.5
      }
    },
    "Elven-Walk-Right-6.png": {
      "frame": {
        "x": 242,
        "y": 53,
        "w": 26,
        "h": 50
      },
      "rotated": false,
      "trimmed": true,
      "spriteSourceSize": {
        "x": 18,
        "y": 14,
        "w": 26,
        "h": 50
      },
      "sourceSize": {
        "w": 64,
        "h": 64
      },
      "pivot": {
        "x": 0.5,
        "y": 0.5
      }
    },
    "Elven-Walk-Right-5.png": {
      "frame": {
        "x": 242,
        "y": 105,
        "w": 27,
        "h": 50
      },
      "rotated": false,
      "trimmed": true,
      "spriteSourceSize": {
        "x": 17,
        "y": 14,
        "w": 27,
        "h": 50
      },
      "sourceSize": {
        "w": 64,
        "h": 64
      },
      "pivot": {
        "x": 0.5,
        "y": 0.5
      }
    },
    "Elven-Walk-Right-4.png": {
      "frame": {
        "x": 240,
        "y": 157,
        "w": 26,
        "h": 50
      },
      "rotated": false,
      "trimmed": true,
      "spriteSourceSize": {
        "x": 18,
        "y": 13,
        "w": 26,
        "h": 50
      },
      "sourceSize": {
        "w": 64,
        "h": 64
      },
      "pivot": {
        "x": 0.5,
        "y": 0.5
      }
    },
    "Elven-Attack-Down-04.png": {
      "frame": {
        "x": 223,
        "y": 217,
        "w": 25,
        "h": 50
      },
      "rotated": false,
      "trimmed": true,
      "spriteSourceSize": {
        "x": 19,
        "y": 14,
        "w": 25,
        "h": 50
      },
      "sourceSize": {
        "w": 64,
        "h": 64
      },
      "pivot": {
        "x": 0.5,
        "y": 0.5
      }
    },
    "Elven-Attack-Down-09.png": {
      "frame": {
        "x": 250,
        "y": 209,
        "w": 25,
        "h": 50
      },
      "rotated": false,
      "trimmed": true,
      "spriteSourceSize": {
        "x": 19,
        "y": 14,
        "w": 25,
        "h": 50
      },
      "sourceSize": {
        "w": 64,
        "h": 64
      },
      "pivot": {
        "x": 0.5,
        "y": 0.5
      }
    },
    "Elven-Attack-Down-03.png": {
      "frame": {
        "x": 270,
        "y": 53,
        "w": 26,
        "h": 50
      },
      "rotated": false,
      "trimmed": true,
      "spriteSourceSize": {
        "x": 18,
        "y": 14,
        "w": 26,
        "h": 50
      },
      "sourceSize": {
        "w": 64,
        "h": 64
      },
      "pivot": {
        "x": 0.5,
        "y": 0.5
      }
    },
    "Elven-Walk-Left-3.png": {
      "frame": {
        "x": 268,
        "y": 157,
        "w": 24,
        "h": 50
      },
      "rotated": false,
      "trimmed": true,
      "spriteSourceSize": {
        "x": 20,
        "y": 12,
        "w": 24,
        "h": 50
      },
      "sourceSize": {
        "w": 64,
        "h": 64
      },
      "pivot": {
        "x": 0.5,
        "y": 0.5
      }
    },
    "Elven-Attack-Right-08.png": {
      "frame": {
        "x": 1,
        "y": 287,
        "w": 44,
        "h": 50
      },
      "rotated": false,
      "trimmed": true,
      "spriteSourceSize": {
        "x": 13,
        "y": 13,
        "w": 44,
        "h": 50
      },
      "sourceSize": {
        "w": 64,
        "h": 64
      },
      "pivot": {
        "x": 0.5,
        "y": 0.5
      }
    },
    "Elven-Attack-Down-10.png": {
      "frame": {
        "x": 283,
        "y": 1,
        "w": 26,
        "h": 50
      },
      "rotated": false,
      "trimmed": true,
      "spriteSourceSize": {
        "x": 18,
        "y": 14,
        "w": 26,
        "h": 50
      },
      "sourceSize": {
        "w": 64,
        "h": 64
      },
      "pivot": {
        "x": 0.5,
        "y": 0.5
      }
    },
    "Elven-Attack-Left-00.png": {
      "frame": {
        "x": 47,
        "y": 287,
        "w": 44,
        "h": 50
      },
      "rotated": false,
      "trimmed": true,
      "spriteSourceSize": {
        "x": 7,
        "y": 13,
        "w": 44,
        "h": 50
      },
      "sourceSize": {
        "w": 64,
        "h": 64
      },
      "pivot": {
        "x": 0.5,
        "y": 0.5
      }
    },
    "Elven-Attack-Left-08.png": {
      "frame": {
        "x": 93,
        "y": 286,
        "w": 43,
        "h": 50
      },
      "rotated": false,
      "trimmed": true,
      "spriteSourceSize": {
        "x": 7,
        "y": 13,
        "w": 43,
        "h": 50
      },
      "sourceSize": {
        "w": 64,
        "h": 64
      },
      "pivot": {
        "x": 0.5,
        "y": 0.5
      }
    },
    "Elven-Attack-Left-01.png": {
      "frame": {
        "x": 271,
        "y": 105,
        "w": 37,
        "h": 50
      },
      "rotated": false,
      "trimmed": true,
      "spriteSourceSize": {
        "x": 12,
        "y": 13,
        "w": 37,
        "h": 50
      },
      "sourceSize": {
        "w": 64,
        "h": 64
      },
      "pivot": {
        "x": 0.5,
        "y": 0.5
      }
    },
    "Elven-Walk-Right-0.png": {
      "frame": {
        "x": 138,
        "y": 282,
        "w": 25,
        "h": 50
      },
      "rotated": false,
      "trimmed": true,
      "spriteSourceSize": {
        "x": 20,
        "y": 13,
        "w": 25,
        "h": 50
      },
      "sourceSize": {
        "w": 64,
        "h": 64
      },
      "pivot": {
        "x": 0.5,
        "y": 0.5
      }
    },
    "Elven-Attack-Up-00.png": {
      "frame": {
        "x": 165,
        "y": 282,
        "w": 43,
        "h": 49
      },
      "rotated": false,
      "trimmed": true,
      "spriteSourceSize": {
        "x": 8,
        "y": 14,
        "w": 43,
        "h": 49
      },
      "sourceSize": {
        "w": 64,
        "h": 64
      },
      "pivot": {
        "x": 0.5,
        "y": 0.5
      }
    },
    "Elven-Attack-Up-01.png": {
      "frame": {
        "x": 210,
        "y": 270,
        "w": 39,
        "h": 49
      },
      "rotated": false,
      "trimmed": true,
      "spriteSourceSize": {
        "x": 11,
        "y": 14,
        "w": 39,
        "h": 49
      },
      "sourceSize": {
        "w": 64,
        "h": 64
      },
      "pivot": {
        "x": 0.5,
        "y": 0.5
      }
    },
    "Elven-Walk-Right-3.png": {
      "frame": {
        "x": 277,
        "y": 209,
        "w": 24,
        "h": 49
      },
      "rotated": false,
      "trimmed": true,
      "spriteSourceSize": {
        "x": 20,
        "y": 13,
        "w": 24,
        "h": 49
      },
      "sourceSize": {
        "w": 64,
        "h": 64
      },
      "pivot": {
        "x": 0.5,
        "y": 0.5
      }
    },
    "Elven-Walk-Right-2.png": {
      "frame": {
        "x": 277,
        "y": 260,
        "w": 24,
        "h": 49
      },
      "rotated": false,
      "trimmed": true,
      "spriteSourceSize": {
        "x": 20,
        "y": 14,
        "w": 24,
        "h": 49
      },
      "sourceSize": {
        "w": 64,
        "h": 64
      },
      "pivot": {
        "x": 0.5,
        "y": 0.5
      }
    },
    "Elven-Walk-Down-1.png": {
      "frame": {
        "x": 311,
        "y": 1,
        "w": 28,
        "h": 49
      },
      "rotated": false,
      "trimmed": true,
      "spriteSourceSize": {
        "x": 18,
        "y": 14,
        "w": 28,
        "h": 49
      },
      "sourceSize": {
        "w": 64,
        "h": 64
      },
      "pivot": {
        "x": 0.5,
        "y": 0.5
      }
    },
    "Elven-Walk-Down-2.png": {
      "frame": {
        "x": 298,
        "y": 53,
        "w": 27,
        "h": 49
      },
      "rotated": false,
      "trimmed": true,
      "spriteSourceSize": {
        "x": 19,
        "y": 14,
        "w": 27,
        "h": 49
      },
      "sourceSize": {
        "w": 64,
        "h": 64
      },
      "pivot": {
        "x": 0.5,
        "y": 0.5
      }
    },
    "Elven-Walk-Down-3.png": {
      "frame": {
        "x": 294,
        "y": 157,
        "w": 26,
        "h": 49
      },
      "rotated": false,
      "trimmed": true,
      "spriteSourceSize": {
        "x": 19,
        "y": 15,
        "w": 26,
        "h": 49
      },
      "sourceSize": {
        "w": 64,
        "h": 64
      },
      "pivot": {
        "x": 0.5,
        "y": 0.5
      }
    },
    "Elven-Walk-Down-4.png": {
      "frame": {
        "x": 310,
        "y": 104,
        "w": 28,
        "h": 49
      },
      "rotated": false,
      "trimmed": true,
      "spriteSourceSize": {
        "x": 18,
        "y": 14,
        "w": 28,
        "h": 49
      },
      "sourceSize": {
        "w": 64,
        "h": 64
      },
      "pivot": {
        "x": 0.5,
        "y": 0.5
      }
    },
    "Elven-Walk-Down-5.png": {
      "frame": {
        "x": 303,
        "y": 208,
        "w": 28,
        "h": 49
      },
      "rotated": false,
      "trimmed": true,
      "spriteSourceSize": {
        "x": 18,
        "y": 14,
        "w": 28,
        "h": 49
      },
      "sourceSize": {
        "w": 64,
        "h": 64
      },
      "pivot": {
        "x": 0.5,
        "y": 0.5
      }
    },
    "Elven-Walk-Down-6.png": {
      "frame": {
        "x": 303,
        "y": 259,
        "w": 27,
        "h": 49
      },
      "rotated": false,
      "trimmed": true,
      "spriteSourceSize": {
        "x": 18,
        "y": 14,
        "w": 27,
        "h": 49
      },
      "sourceSize": {
        "w": 64,
        "h": 64
      },
      "pivot": {
        "x": 0.5,
        "y": 0.5
      }
    },
    "Elven-Walk-Down-7.png": {
      "frame": {
        "x": 1,
        "y": 339,
        "w": 26,
        "h": 49
      },
      "rotated": false,
      "trimmed": true,
      "spriteSourceSize": {
        "x": 19,
        "y": 15,
        "w": 26,
        "h": 49
      },
      "sourceSize": {
        "w": 64,
        "h": 64
      },
      "pivot": {
        "x": 0.5,
        "y": 0.5
      }
    },
    "Elven-Walk-Down-8.png": {
      "frame": {
        "x": 29,
        "y": 339,
        "w": 28,
        "h": 49
      },
      "rotated": false,
      "trimmed": true,
      "spriteSourceSize": {
        "x": 18,
        "y": 14,
        "w": 28,
        "h": 49
      },
      "sourceSize": {
        "w": 64,
        "h": 64
      },
      "pivot": {
        "x": 0.5,
        "y": 0.5
      }
    },
    "Elven-Attack-Up-02.png": {
      "frame": {
        "x": 303,
        "y": 310,
        "w": 36,
        "h": 49
      },
      "rotated": false,
      "trimmed": true,
      "spriteSourceSize": {
        "x": 15,
        "y": 15,
        "w": 36,
        "h": 49
      },
      "sourceSize": {
        "w": 64,
        "h": 64
      },
      "pivot": {
        "x": 0.5,
        "y": 0.5
      }
    },
    "Elven-Attack-Down-01.png": {
      "frame": {
        "x": 59,
        "y": 339,
        "w": 34,
        "h": 49
      },
      "rotated": false,
      "trimmed": true,
      "spriteSourceSize": {
        "x": 12,
        "y": 14,
        "w": 34,
        "h": 49
      },
      "sourceSize": {
        "w": 64,
        "h": 64
      },
      "pivot": {
        "x": 0.5,
        "y": 0.5
      }
    },
    "Elven-Attack-Down-02.png": {
      "frame": {
        "x": 95,
        "y": 338,
        "w": 36,
        "h": 49
      },
      "rotated": false,
      "trimmed": true,
      "spriteSourceSize": {
        "x": 13,
        "y": 14,
        "w": 36,
        "h": 49
      },
      "sourceSize": {
        "w": 64,
        "h": 64
      },
      "pivot": {
        "x": 0.5,
        "y": 0.5
      }
    },
    "Elven-Walk-Down-0.png": {
      "frame": {
        "x": 133,
        "y": 338,
        "w": 28,
        "h": 49
      },
      "rotated": false,
      "trimmed": true,
      "spriteSourceSize": {
        "x": 18,
        "y": 14,
        "w": 28,
        "h": 49
      },
      "sourceSize": {
        "w": 64,
        "h": 64
      },
      "pivot": {
        "x": 0.5,
        "y": 0.5
      }
    },
    "Elven-Attack-Down-00.png": {
      "frame": {
        "x": 163,
        "y": 334,
        "w": 39,
        "h": 49
      },
      "rotated": false,
      "trimmed": true,
      "spriteSourceSize": {
        "x": 15,
        "y": 14,
        "w": 39,
        "h": 49
      },
      "sourceSize": {
        "w": 64,
        "h": 64
      },
      "pivot": {
        "x": 0.5,
        "y": 0.5
      }
    },
    "Elven-Attack-Down-05.png": {
      "frame": {
        "x": 204,
        "y": 333,
        "w": 25,
        "h": 49
      },
      "rotated": false,
      "trimmed": true,
      "spriteSourceSize": {
        "x": 19,
        "y": 14,
        "w": 25,
        "h": 49
      },
      "sourceSize": {
        "w": 64,
        "h": 64
      },
      "pivot": {
        "x": 0.5,
        "y": 0.5
      }
    },
    "Elven-Attack-Down-06.png": {
      "frame": {
        "x": 231,
        "y": 321,
        "w": 25,
        "h": 49
      },
      "rotated": false,
      "trimmed": true,
      "spriteSourceSize": {
        "x": 19,
        "y": 14,
        "w": 25,
        "h": 49
      },
      "sourceSize": {
        "w": 64,
        "h": 64
      },
      "pivot": {
        "x": 0.5,
        "y": 0.5
      }
    },
    "Elven-Attack-Down-07.png": {
      "frame": {
        "x": 258,
        "y": 311,
        "w": 26,
        "h": 49
      },
      "rotated": false,
      "trimmed": true,
      "spriteSourceSize": {
        "x": 18,
        "y": 14,
        "w": 26,
        "h": 49
      },
      "sourceSize": {
        "w": 64,
        "h": 64
      },
      "pivot": {
        "x": 0.5,
        "y": 0.5
      }
    },
    "Elven-Attack-Down-08.png": {
      "frame": {
        "x": 332,
        "y": 259,
        "w": 26,
        "h": 49
      },
      "rotated": false,
      "trimmed": true,
      "spriteSourceSize": {
        "x": 18,
        "y": 14,
        "w": 26,
        "h": 49
      },
      "sourceSize": {
        "w": 64,
        "h": 64
      },
      "pivot": {
        "x": 0.5,
        "y": 0.5
      }
    },
    "Elven-Dead-Down-0.png": {
      "frame": {
        "x": 327,
        "y": 52,
        "w": 28,
        "h": 49
      },
      "rotated": false,
      "trimmed": true,
      "spriteSourceSize": {
        "x": 18,
        "y": 15,
        "w": 28,
        "h": 49
      },
      "sourceSize": {
        "w": 64,
        "h": 64
      },
      "pivot": {
        "x": 0.5,
        "y": 0.5
      }
    },
    "Elven-Walk-Right-1.png": {
      "frame": {
        "x": 341,
        "y": 1,
        "w": 24,
        "h": 49
      },
      "rotated": false,
      "trimmed": true,
      "spriteSourceSize": {
        "x": 20,
        "y": 14,
        "w": 24,
        "h": 49
      },
      "sourceSize": {
        "w": 64,
        "h": 64
      },
      "pivot": {
        "x": 0.5,
        "y": 0.5
      }
    },
    "Elven-Attack-Right-03.png": {
      "frame": {
        "x": 322,
        "y": 155,
        "w": 39,
        "h": 48
      },
      "rotated": false,
      "trimmed": true,
      "spriteSourceSize": {
        "x": 16,
        "y": 15,
        "w": 39,
        "h": 48
      },
      "sourceSize": {
        "w": 64,
        "h": 64
      },
      "pivot": {
        "x": 0.5,
        "y": 0.5
      }
    },
    "Elven-Attack-Left-03.png": {
      "frame": {
        "x": 367,
        "y": 1,
        "w": 38,
        "h": 48
      },
      "rotated": false,
      "trimmed": true,
      "spriteSourceSize": {
        "x": 9,
        "y": 15,
        "w": 38,
        "h": 48
      },
      "sourceSize": {
        "w": 64,
        "h": 64
      },
      "pivot": {
        "x": 0.5,
        "y": 0.5
      }
    },
    "Elven-Walk-Up-3.png": {
      "frame": {
        "x": 340,
        "y": 103,
        "w": 26,
        "h": 48
      },
      "rotated": false,
      "trimmed": true,
      "spriteSourceSize": {
        "x": 19,
        "y": 16,
        "w": 26,
        "h": 48
      },
      "sourceSize": {
        "w": 64,
        "h": 64
      },
      "pivot": {
        "x": 0.5,
        "y": 0.5
      }
    },
    "Elven-Walk-Up-7.png": {
      "frame": {
        "x": 357,
        "y": 52,
        "w": 26,
        "h": 48
      },
      "rotated": false,
      "trimmed": true,
      "spriteSourceSize": {
        "x": 19,
        "y": 16,
        "w": 26,
        "h": 48
      },
      "sourceSize": {
        "w": 64,
        "h": 64
      },
      "pivot": {
        "x": 0.5,
        "y": 0.5
      }
    },
    "Elven-Walk-Up-8.png": {
      "frame": {
        "x": 333,
        "y": 205,
        "w": 28,
        "h": 47
      },
      "rotated": false,
      "trimmed": true,
      "spriteSourceSize": {
        "x": 18,
        "y": 16,
        "w": 28,
        "h": 47
      },
      "sourceSize": {
        "w": 64,
        "h": 64
      },
      "pivot": {
        "x": 0.5,
        "y": 0.5
      }
    },
    "Orc-Dead-Down-0.png": {
      "frame": {
        "x": 368,
        "y": 102,
        "w": 30,
        "h": 47
      },
      "rotated": false,
      "trimmed": true,
      "spriteSourceSize": {
        "x": 17,
        "y": 17,
        "w": 30,
        "h": 47
      },
      "sourceSize": {
        "w": 64,
        "h": 64
      },
      "pivot": {
        "x": 0.5,
        "y": 0.5
      }
    },
    "Orc-Walk-Down-0.png": {
      "frame": {
        "x": 368,
        "y": 151,
        "w": 30,
        "h": 47
      },
      "rotated": false,
      "trimmed": true,
      "spriteSourceSize": {
        "x": 17,
        "y": 17,
        "w": 30,
        "h": 47
      },
      "sourceSize": {
        "w": 64,
        "h": 64
      },
      "pivot": {
        "x": 0.5,
        "y": 0.5
      }
    },
    "Orc-Walk-Down-4.png": {
      "frame": {
        "x": 363,
        "y": 200,
        "w": 30,
        "h": 47
      },
      "rotated": false,
      "trimmed": true,
      "spriteSourceSize": {
        "x": 17,
        "y": 17,
        "w": 30,
        "h": 47
      },
      "sourceSize": {
        "w": 64,
        "h": 64
      },
      "pivot": {
        "x": 0.5,
        "y": 0.5
      }
    },
    "Orc-Walk-Down-5.png": {
      "frame": {
        "x": 363,
        "y": 249,
        "w": 30,
        "h": 47
      },
      "rotated": false,
      "trimmed": true,
      "spriteSourceSize": {
        "x": 17,
        "y": 17,
        "w": 30,
        "h": 47
      },
      "sourceSize": {
        "w": 64,
        "h": 64
      },
      "pivot": {
        "x": 0.5,
        "y": 0.5
      }
    },
    "Elven-Walk-Up-2.png": {
      "frame": {
        "x": 360,
        "y": 298,
        "w": 26,
        "h": 47
      },
      "rotated": false,
      "trimmed": true,
      "spriteSourceSize": {
        "x": 19,
        "y": 16,
        "w": 26,
        "h": 47
      },
      "sourceSize": {
        "w": 64,
        "h": 64
      },
      "pivot": {
        "x": 0.5,
        "y": 0.5
      }
    },
    "Elven-Dead-Down-1.png": {
      "frame": {
        "x": 1,
        "y": 390,
        "w": 27,
        "h": 47
      },
      "rotated": false,
      "trimmed": true,
      "spriteSourceSize": {
        "x": 20,
        "y": 15,
        "w": 27,
        "h": 47
      },
      "sourceSize": {
        "w": 64,
        "h": 64
      },
      "pivot": {
        "x": 0.5,
        "y": 0.5
      }
    },
    "Elven-Walk-Up-4.png": {
      "frame": {
        "x": 30,
        "y": 390,
        "w": 28,
        "h": 47
      },
      "rotated": false,
      "trimmed": true,
      "spriteSourceSize": {
        "x": 18,
        "y": 16,
        "w": 28,
        "h": 47
      },
      "sourceSize": {
        "w": 64,
        "h": 64
      },
      "pivot": {
        "x": 0.5,
        "y": 0.5
      }
    },
    "Orc-Attack-Down-1.png": {
      "frame": {
        "x": 60,
        "y": 390,
        "w": 27,
        "h": 47
      },
      "rotated": false,
      "trimmed": true,
      "spriteSourceSize": {
        "x": 19,
        "y": 17,
        "w": 27,
        "h": 47
      },
      "sourceSize": {
        "w": 64,
        "h": 64
      },
      "pivot": {
        "x": 0.5,
        "y": 0.5
      }
    },
    "Elven-Walk-Up-6.png": {
      "frame": {
        "x": 89,
        "y": 390,
        "w": 26,
        "h": 47
      },
      "rotated": false,
      "trimmed": true,
      "spriteSourceSize": {
        "x": 19,
        "y": 16,
        "w": 26,
        "h": 47
      },
      "sourceSize": {
        "w": 64,
        "h": 64
      },
      "pivot": {
        "x": 0.5,
        "y": 0.5
      }
    },
    "Orc-Walk-Down-1.png": {
      "frame": {
        "x": 117,
        "y": 389,
        "w": 30,
        "h": 47
      },
      "rotated": false,
      "trimmed": true,
      "spriteSourceSize": {
        "x": 17,
        "y": 17,
        "w": 30,
        "h": 47
      },
      "sourceSize": {
        "w": 64,
        "h": 64
      },
      "pivot": {
        "x": 0.5,
        "y": 0.5
      }
    },
    "Orc-Walk-Down-8.png": {
      "frame": {
        "x": 149,
        "y": 389,
        "w": 30,
        "h": 47
      },
      "rotated": false,
      "trimmed": true,
      "spriteSourceSize": {
        "x": 17,
        "y": 17,
        "w": 30,
        "h": 47
      },
      "sourceSize": {
        "w": 64,
        "h": 64
      },
      "pivot": {
        "x": 0.5,
        "y": 0.5
      }
    },
    "Orc-Attack-Down-0.png": {
      "frame": {
        "x": 181,
        "y": 385,
        "w": 30,
        "h": 47
      },
      "rotated": false,
      "trimmed": true,
      "spriteSourceSize": {
        "x": 17,
        "y": 17,
        "w": 30,
        "h": 47
      },
      "sourceSize": {
        "w": 64,
        "h": 64
      },
      "pivot": {
        "x": 0.5,
        "y": 0.5
      }
    },
    "Elven-Walk-Up-0.png": {
      "frame": {
        "x": 213,
        "y": 384,
        "w": 28,
        "h": 46
      },
      "rotated": false,
      "trimmed": true,
      "spriteSourceSize": {
        "x": 18,
        "y": 16,
        "w": 28,
        "h": 46
      },
      "sourceSize": {
        "w": 64,
        "h": 64
      },
      "pivot": {
        "x": 0.5,
        "y": 0.5
      }
    },
    "Elven-Walk-Up-5.png": {
      "frame": {
        "x": 243,
        "y": 372,
        "w": 28,
        "h": 46
      },
      "rotated": false,
      "trimmed": true,
      "spriteSourceSize": {
        "x": 18,
        "y": 16,
        "w": 28,
        "h": 46
      },
      "sourceSize": {
        "w": 64,
        "h": 64
      },
      "pivot": {
        "x": 0.5,
        "y": 0.5
      }
    },
    "Orc-Dead-Down-1.png": {
      "frame": {
        "x": 273,
        "y": 362,
        "w": 31,
        "h": 46
      },
      "rotated": false,
      "trimmed": true,
      "spriteSourceSize": {
        "x": 18,
        "y": 18,
        "w": 31,
        "h": 46
      },
      "sourceSize": {
        "w": 64,
        "h": 64
      },
      "pivot": {
        "x": 0.5,
        "y": 0.5
      }
    },
    "Orc-Attack-Down-4.png": {
      "frame": {
        "x": 306,
        "y": 361,
        "w": 35,
        "h": 46
      },
      "rotated": false,
      "trimmed": true,
      "spriteSourceSize": {
        "x": 20,
        "y": 17,
        "w": 35,
        "h": 46
      },
      "sourceSize": {
        "w": 64,
        "h": 64
      },
      "pivot": {
        "x": 0.5,
        "y": 0.5
      }
    },
    "Orc-Attack-Down-5.png": {
      "frame": {
        "x": 343,
        "y": 347,
        "w": 44,
        "h": 46
      },
      "rotated": false,
      "trimmed": true,
      "spriteSourceSize": {
        "x": 19,
        "y": 17,
        "w": 44,
        "h": 46
      },
      "sourceSize": {
        "w": 64,
        "h": 64
      },
      "pivot": {
        "x": 0.5,
        "y": 0.5
      }
    },
    "Orc-Walk-Down-6.png": {
      "frame": {
        "x": 388,
        "y": 298,
        "w": 30,
        "h": 46
      },
      "rotated": false,
      "trimmed": true,
      "spriteSourceSize": {
        "x": 17,
        "y": 17,
        "w": 30,
        "h": 46
      },
      "sourceSize": {
        "w": 64,
        "h": 64
      },
      "pivot": {
        "x": 0.5,
        "y": 0.5
      }
    },
    "Elven-Walk-Up-1.png": {
      "frame": {
        "x": 385,
        "y": 51,
        "w": 28,
        "h": 46
      },
      "rotated": false,
      "trimmed": true,
      "spriteSourceSize": {
        "x": 18,
        "y": 16,
        "w": 28,
        "h": 46
      },
      "sourceSize": {
        "w": 64,
        "h": 64
      },
      "pivot": {
        "x": 0.5,
        "y": 0.5
      }
    },
    "Orc-Walk-Down-7.png": {
      "frame": {
        "x": 407,
        "y": 1,
        "w": 29,
        "h": 46
      },
      "rotated": false,
      "trimmed": true,
      "spriteSourceSize": {
        "x": 17,
        "y": 17,
        "w": 29,
        "h": 46
      },
      "sourceSize": {
        "w": 64,
        "h": 64
      },
      "pivot": {
        "x": 0.5,
        "y": 0.5
      }
    },
    "Orc-Walk-Down-3.png": {
      "frame": {
        "x": 400,
        "y": 99,
        "w": 29,
        "h": 46
      },
      "rotated": false,
      "trimmed": true,
      "spriteSourceSize": {
        "x": 18,
        "y": 17,
        "w": 29,
        "h": 46
      },
      "sourceSize": {
        "w": 64,
        "h": 64
      },
      "pivot": {
        "x": 0.5,
        "y": 0.5
      }
    },
    "Orc-Walk-Down-2.png": {
      "frame": {
        "x": 400,
        "y": 147,
        "w": 30,
        "h": 46
      },
      "rotated": false,
      "trimmed": true,
      "spriteSourceSize": {
        "x": 17,
        "y": 17,
        "w": 30,
        "h": 46
      },
      "sourceSize": {
        "w": 64,
        "h": 64
      },
      "pivot": {
        "x": 0.5,
        "y": 0.5
      }
    },
    "Orc-Attack-Down-2.png": {
      "frame": {
        "x": 400,
        "y": 195,
        "w": 28,
        "h": 45
      },
      "rotated": false,
      "trimmed": true,
      "spriteSourceSize": {
        "x": 18,
        "y": 19,
        "w": 28,
        "h": 45
      },
      "sourceSize": {
        "w": 64,
        "h": 64
      },
      "pivot": {
        "x": 0.5,
        "y": 0.5
      }
    },
    "Orc-Walk-Up-3.png": {
      "frame": {
        "x": 395,
        "y": 242,
        "w": 29,
        "h": 45
      },
      "rotated": false,
      "trimmed": true,
      "spriteSourceSize": {
        "x": 17,
        "y": 18,
        "w": 29,
        "h": 45
      },
      "sourceSize": {
        "w": 64,
        "h": 64
      },
      "pivot": {
        "x": 0.5,
        "y": 0.5
      }
    },
    "Orc-Attack-Down-3.png": {
      "frame": {
        "x": 389,
        "y": 346,
        "w": 26,
        "h": 45
      },
      "rotated": false,
      "trimmed": true,
      "spriteSourceSize": {
        "x": 20,
        "y": 18,
        "w": 26,
        "h": 45
      },
      "sourceSize": {
        "w": 64,
        "h": 64
      },
      "pivot": {
        "x": 0.5,
        "y": 0.5
      }
    },
    "Orc-Walk-Up-7.png": {
      "frame": {
        "x": 1,
        "y": 439,
        "w": 29,
        "h": 45
      },
      "rotated": false,
      "trimmed": true,
      "spriteSourceSize": {
        "x": 18,
        "y": 18,
        "w": 29,
        "h": 45
      },
      "sourceSize": {
        "w": 64,
        "h": 64
      },
      "pivot": {
        "x": 0.5,
        "y": 0.5
      }
    },
    "Orc-Attack-Left-5.png": {
      "frame": {
        "x": 32,
        "y": 439,
        "w": 43,
        "h": 44
      },
      "rotated": false,
      "trimmed": true,
      "spriteSourceSize": {
        "x": 1,
        "y": 20,
        "w": 43,
        "h": 44
      },
      "sourceSize": {
        "w": 64,
        "h": 64
      },
      "pivot": {
        "x": 0.5,
        "y": 0.5
      }
    },
    "Orc-Walk-Up-4.png": {
      "frame": {
        "x": 77,
        "y": 439,
        "w": 30,
        "h": 44
      },
      "rotated": false,
      "trimmed": true,
      "spriteSourceSize": {
        "x": 17,
        "y": 18,
        "w": 30,
        "h": 44
      },
      "sourceSize": {
        "w": 64,
        "h": 64
      },
      "pivot": {
        "x": 0.5,
        "y": 0.5
      }
    },
    "Orc-Walk-Up-8.png": {
      "frame": {
        "x": 109,
        "y": 439,
        "w": 30,
        "h": 44
      },
      "rotated": false,
      "trimmed": true,
      "spriteSourceSize": {
        "x": 17,
        "y": 18,
        "w": 30,
        "h": 44
      },
      "sourceSize": {
        "w": 64,
        "h": 64
      },
      "pivot": {
        "x": 0.5,
        "y": 0.5
      }
    },
    "Orc-Attack-Right-2.png": {
      "frame": {
        "x": 141,
        "y": 438,
        "w": 25,
        "h": 44
      },
      "rotated": false,
      "trimmed": true,
      "spriteSourceSize": {
        "x": 20,
        "y": 20,
        "w": 25,
        "h": 44
      },
      "sourceSize": {
        "w": 64,
        "h": 64
      },
      "pivot": {
        "x": 0.5,
        "y": 0.5
      }
    },
    "Orc-Attack-Right-3.png": {
      "frame": {
        "x": 168,
        "y": 438,
        "w": 38,
        "h": 44
      },
      "rotated": false,
      "trimmed": true,
      "spriteSourceSize": {
        "x": 19,
        "y": 20,
        "w": 38,
        "h": 44
      },
      "sourceSize": {
        "w": 64,
        "h": 64
      },
      "pivot": {
        "x": 0.5,
        "y": 0.5
      }
    },
    "Orc-Attack-Right-4.png": {
      "frame": {
        "x": 389,
        "y": 393,
        "w": 44,
        "h": 44
      },
      "rotated": false,
      "trimmed": true,
      "spriteSourceSize": {
        "x": 20,
        "y": 20,
        "w": 44,
        "h": 44
      },
      "sourceSize": {
        "w": 64,
        "h": 64
      },
      "pivot": {
        "x": 0.5,
        "y": 0.5
      }
    },
    "Orc-Attack-Right-5.png": {
      "frame": {
        "x": 343,
        "y": 395,
        "w": 43,
        "h": 44
      },
      "rotated": false,
      "trimmed": true,
      "spriteSourceSize": {
        "x": 20,
        "y": 20,
        "w": 43,
        "h": 44
      },
      "sourceSize": {
        "w": 64,
        "h": 64
      },
      "pivot": {
        "x": 0.5,
        "y": 0.5
      }
    },
    "Orc-Walk-Up-2.png": {
      "frame": {
        "x": 388,
        "y": 439,
        "w": 30,
        "h": 44
      },
      "rotated": false,
      "trimmed": true,
      "spriteSourceSize": {
        "x": 17,
        "y": 18,
        "w": 30,
        "h": 44
      },
      "sourceSize": {
        "w": 64,
        "h": 64
      },
      "pivot": {
        "x": 0.5,
        "y": 0.5
      }
    },
    "Orc-Walk-Up-6.png": {
      "frame": {
        "x": 306,
        "y": 409,
        "w": 30,
        "h": 44
      },
      "rotated": false,
      "trimmed": true,
      "spriteSourceSize": {
        "x": 17,
        "y": 18,
        "w": 30,
        "h": 44
      },
      "sourceSize": {
        "w": 64,
        "h": 64
      },
      "pivot": {
        "x": 0.5,
        "y": 0.5
      }
    },
    "Orc-Attack-Left-2.png": {
      "frame": {
        "x": 273,
        "y": 410,
        "w": 25,
        "h": 44
      },
      "rotated": false,
      "trimmed": true,
      "spriteSourceSize": {
        "x": 19,
        "y": 20,
        "w": 25,
        "h": 44
      },
      "sourceSize": {
        "w": 64,
        "h": 64
      },
      "pivot": {
        "x": 0.5,
        "y": 0.5
      }
    },
    "Orc-Attack-Left-3.png": {
      "frame": {
        "x": 208,
        "y": 434,
        "w": 38,
        "h": 44
      },
      "rotated": false,
      "trimmed": true,
      "spriteSourceSize": {
        "x": 7,
        "y": 20,
        "w": 38,
        "h": 44
      },
      "sourceSize": {
        "w": 64,
        "h": 64
      },
      "pivot": {
        "x": 0.5,
        "y": 0.5
      }
    },
    "Orc-Attack-Left-4.png": {
      "frame": {
        "x": 417,
        "y": 346,
        "w": 44,
        "h": 44
      },
      "rotated": false,
      "trimmed": true,
      "spriteSourceSize": {
        "x": 0,
        "y": 20,
        "w": 44,
        "h": 44
      },
      "sourceSize": {
        "w": 64,
        "h": 64
      },
      "pivot": {
        "x": 0.5,
        "y": 0.5
      }
    },
    "Orc-Walk-Up-5.png": {
      "frame": {
        "x": 338,
        "y": 441,
        "w": 30,
        "h": 43
      },
      "rotated": false,
      "trimmed": true,
      "spriteSourceSize": {
        "x": 17,
        "y": 18,
        "w": 30,
        "h": 43
      },
      "sourceSize": {
        "w": 64,
        "h": 64
      },
      "pivot": {
        "x": 0.5,
        "y": 0.5
      }
    },
    "Orc-Walk-Up-1.png": {
      "frame": {
        "x": 420,
        "y": 439,
        "w": 30,
        "h": 43
      },
      "rotated": false,
      "trimmed": true,
      "spriteSourceSize": {
        "x": 17,
        "y": 18,
        "w": 30,
        "h": 43
      },
      "sourceSize": {
        "w": 64,
        "h": 64
      },
      "pivot": {
        "x": 0.5,
        "y": 0.5
      }
    },
    "Orc-Walk-Up-0.png": {
      "frame": {
        "x": 435,
        "y": 392,
        "w": 30,
        "h": 43
      },
      "rotated": false,
      "trimmed": true,
      "spriteSourceSize": {
        "x": 17,
        "y": 18,
        "w": 30,
        "h": 43
      },
      "sourceSize": {
        "w": 64,
        "h": 64
      },
      "pivot": {
        "x": 0.5,
        "y": 0.5
      }
    },
    "Orc-Attack-Right-0.png": {
      "frame": {
        "x": 452,
        "y": 437,
        "w": 31,
        "h": 43
      },
      "rotated": false,
      "trimmed": true,
      "spriteSourceSize": {
        "x": 21,
        "y": 20,
        "w": 31,
        "h": 43
      },
      "sourceSize": {
        "w": 64,
        "h": 64
      },
      "pivot": {
        "x": 0.5,
        "y": 0.5
      }
    },
    "Orc-Attack-Left-0.png": {
      "frame": {
        "x": 415,
        "y": 49,
        "w": 31,
        "h": 43
      },
      "rotated": false,
      "trimmed": true,
      "spriteSourceSize": {
        "x": 12,
        "y": 20,
        "w": 31,
        "h": 43
      },
      "sourceSize": {
        "w": 64,
        "h": 64
      },
      "pivot": {
        "x": 0.5,
        "y": 0.5
      }
    },
    "Orc-Walk-Left-0.png": {
      "frame": {
        "x": 438,
        "y": 1,
        "w": 31,
        "h": 43
      },
      "rotated": false,
      "trimmed": true,
      "spriteSourceSize": {
        "x": 12,
        "y": 20,
        "w": 31,
        "h": 43
      },
      "sourceSize": {
        "w": 64,
        "h": 64
      },
      "pivot": {
        "x": 0.5,
        "y": 0.5
      }
    },
    "Orc-Walk-Right-0.png": {
      "frame": {
        "x": 448,
        "y": 46,
        "w": 31,
        "h": 43
      },
      "rotated": false,
      "trimmed": true,
      "spriteSourceSize": {
        "x": 21,
        "y": 20,
        "w": 31,
        "h": 43
      },
      "sourceSize": {
        "w": 64,
        "h": 64
      },
      "pivot": {
        "x": 0.5,
        "y": 0.5
      }
    },
    "Orc-Walk-Left-5.png": {
      "frame": {
        "x": 431,
        "y": 94,
        "w": 28,
        "h": 42
      },
      "rotated": false,
      "trimmed": true,
      "spriteSourceSize": {
        "x": 20,
        "y": 20,
        "w": 28,
        "h": 42
      },
      "sourceSize": {
        "w": 64,
        "h": 64
      },
      "pivot": {
        "x": 0.5,
        "y": 0.5
      }
    },
    "Orc-Walk-Right-7.png": {
      "frame": {
        "x": 420,
        "y": 289,
        "w": 31,
        "h": 42
      },
      "rotated": false,
      "trimmed": true,
      "spriteSourceSize": {
        "x": 19,
        "y": 20,
        "w": 31,
        "h": 42
      },
      "sourceSize": {
        "w": 64,
        "h": 64
      },
      "pivot": {
        "x": 0.5,
        "y": 0.5
      }
    },
    "Orc-Walk-Right-6.png": {
      "frame": {
        "x": 453,
        "y": 138,
        "w": 30,
        "h": 42
      },
      "rotated": false,
      "trimmed": true,
      "spriteSourceSize": {
        "x": 18,
        "y": 20,
        "w": 30,
        "h": 42
      },
      "sourceSize": {
        "w": 64,
        "h": 64
      },
      "pivot": {
        "x": 0.5,
        "y": 0.5
      }
    },
    "Orc-Attack-Right-1.png": {
      "frame": {
        "x": 453,
        "y": 182,
        "w": 31,
        "h": 42
      },
      "rotated": false,
      "trimmed": true,
      "spriteSourceSize": {
        "x": 22,
        "y": 22,
        "w": 31,
        "h": 42
      },
      "sourceSize": {
        "w": 64,
        "h": 64
      },
      "pivot": {
        "x": 0.5,
        "y": 0.5
      }
    },
    "Elven-Dead-Down-2.png": {
      "frame": {
        "x": 426,
        "y": 242,
        "w": 27,
        "h": 42
      },
      "rotated": false,
      "trimmed": true,
      "spriteSourceSize": {
        "x": 20,
        "y": 22,
        "w": 27,
        "h": 42
      },
      "sourceSize": {
        "w": 64,
        "h": 64
      },
      "pivot": {
        "x": 0.5,
        "y": 0.5
      }
    },
    "Orc-Attack-Left-1.png": {
      "frame": {
        "x": 453,
        "y": 286,
        "w": 31,
        "h": 42
      },
      "rotated": false,
      "trimmed": true,
      "spriteSourceSize": {
        "x": 11,
        "y": 22,
        "w": 31,
        "h": 42
      },
      "sourceSize": {
        "w": 64,
        "h": 64
      },
      "pivot": {
        "x": 0.5,
        "y": 0.5
      }
    },
    "Orc-Attack-Up-3.png": {
      "frame": {
        "x": 455,
        "y": 226,
        "w": 27,
        "h": 42
      },
      "rotated": false,
      "trimmed": true,
      "spriteSourceSize": {
        "x": 19,
        "y": 21,
        "w": 27,
        "h": 42
      },
      "sourceSize": {
        "w": 64,
        "h": 64
      },
      "pivot": {
        "x": 0.5,
        "y": 0.5
      }
    },
    "Orc-Walk-Right-5.png": {
      "frame": {
        "x": 1,
        "y": 486,
        "w": 28,
        "h": 42
      },
      "rotated": false,
      "trimmed": true,
      "spriteSourceSize": {
        "x": 16,
        "y": 20,
        "w": 28,
        "h": 42
      },
      "sourceSize": {
        "w": 64,
        "h": 64
      },
      "pivot": {
        "x": 0.5,
        "y": 0.5
      }
    },
    "Orc-Walk-Right-4.png": {
      "frame": {
        "x": 31,
        "y": 486,
        "w": 31,
        "h": 42
      },
      "rotated": false,
      "trimmed": true,
      "spriteSourceSize": {
        "x": 18,
        "y": 20,
        "w": 31,
        "h": 42
      },
      "sourceSize": {
        "w": 64,
        "h": 64
      },
      "pivot": {
        "x": 0.5,
        "y": 0.5
      }
    },
    "Orc-Attack-Up-5.png": {
      "frame": {
        "x": 64,
        "y": 486,
        "w": 39,
        "h": 42
      },
      "rotated": false,
      "trimmed": true,
      "spriteSourceSize": {
        "x": 18,
        "y": 21,
        "w": 39,
        "h": 42
      },
      "sourceSize": {
        "w": 64,
        "h": 64
      },
      "pivot": {
        "x": 0.5,
        "y": 0.5
      }
    },
    "Orc-Walk-Left-1.png": {
      "frame": {
        "x": 105,
        "y": 486,
        "w": 26,
        "h": 42
      },
      "rotated": false,
      "trimmed": true,
      "spriteSourceSize": {
        "x": 18,
        "y": 20,
        "w": 26,
        "h": 42
      },
      "sourceSize": {
        "w": 64,
        "h": 64
      },
      "pivot": {
        "x": 0.5,
        "y": 0.5
      }
    },
    "Orc-Walk-Right-1.png": {
      "frame": {
        "x": 133,
        "y": 486,
        "w": 26,
        "h": 42
      },
      "rotated": false,
      "trimmed": true,
      "spriteSourceSize": {
        "x": 20,
        "y": 20,
        "w": 26,
        "h": 42
      },
      "sourceSize": {
        "w": 64,
        "h": 64
      },
      "pivot": {
        "x": 0.5,
        "y": 0.5
      }
    },
    "Orc-Walk-Right-8.png": {
      "frame": {
        "x": 463,
        "y": 330,
        "w": 22,
        "h": 42
      },
      "rotated": false,
      "trimmed": true,
      "spriteSourceSize": {
        "x": 20,
        "y": 20,
        "w": 22,
        "h": 42
      },
      "sourceSize": {
        "w": 64,
        "h": 64
      },
      "pivot": {
        "x": 0.5,
        "y": 0.5
      }
    },
    "Orc-Walk-Left-4.png": {
      "frame": {
        "x": 161,
        "y": 486,
        "w": 31,
        "h": 42
      },
      "rotated": false,
      "trimmed": true,
      "spriteSourceSize": {
        "x": 15,
        "y": 20,
        "w": 31,
        "h": 42
      },
      "sourceSize": {
        "w": 64,
        "h": 64
      },
      "pivot": {
        "x": 0.5,
        "y": 0.5
      }
    },
    "Orc-Attack-Up-4.png": {
      "frame": {
        "x": 300,
        "y": 455,
        "w": 36,
        "h": 42
      },
      "rotated": false,
      "trimmed": true,
      "spriteSourceSize": {
        "x": 18,
        "y": 21,
        "w": 36,
        "h": 42
      },
      "sourceSize": {
        "w": 64,
        "h": 64
      },
      "pivot": {
        "x": 0.5,
        "y": 0.5
      }
    },
    "Orc-Walk-Left-6.png": {
      "frame": {
        "x": 338,
        "y": 486,
        "w": 30,
        "h": 42
      },
      "rotated": false,
      "trimmed": true,
      "spriteSourceSize": {
        "x": 16,
        "y": 20,
        "w": 30,
        "h": 42
      },
      "sourceSize": {
        "w": 64,
        "h": 64
      },
      "pivot": {
        "x": 0.5,
        "y": 0.5
      }
    },
    "Orc-Walk-Left-7.png": {
      "frame": {
        "x": 370,
        "y": 485,
        "w": 31,
        "h": 42
      },
      "rotated": false,
      "trimmed": true,
      "spriteSourceSize": {
        "x": 14,
        "y": 20,
        "w": 31,
        "h": 42
      },
      "sourceSize": {
        "w": 64,
        "h": 64
      },
      "pivot": {
        "x": 0.5,
        "y": 0.5
      }
    },
    "Orc-Walk-Left-8.png": {
      "frame": {
        "x": 248,
        "y": 420,
        "w": 22,
        "h": 42
      },
      "rotated": false,
      "trimmed": true,
      "spriteSourceSize": {
        "x": 22,
        "y": 20,
        "w": 22,
        "h": 42
      },
      "sourceSize": {
        "w": 64,
        "h": 64
      },
      "pivot": {
        "x": 0.5,
        "y": 0.5
      }
    },
    "Orc-Walk-Left-3.png": {
      "frame": {
        "x": 251,
        "y": 261,
        "w": 23,
        "h": 41
      },
      "rotated": false,
      "trimmed": true,
      "spriteSourceSize": {
        "x": 22,
        "y": 20,
        "w": 23,
        "h": 41
      },
      "sourceSize": {
        "w": 64,
        "h": 64
      },
      "pivot": {
        "x": 0.5,
        "y": 0.5
      }
    },
    "Orc-Walk-Right-2.png": {
      "frame": {
        "x": 461,
        "y": 91,
        "w": 23,
        "h": 41
      },
      "rotated": false,
      "trimmed": true,
      "spriteSourceSize": {
        "x": 21,
        "y": 20,
        "w": 23,
        "h": 41
      },
      "sourceSize": {
        "w": 64,
        "h": 64
      },
      "pivot": {
        "x": 0.5,
        "y": 0.5
      }
    },
    "Orc-Walk-Right-3.png": {
      "frame": {
        "x": 403,
        "y": 485,
        "w": 23,
        "h": 41
      },
      "rotated": false,
      "trimmed": true,
      "spriteSourceSize": {
        "x": 19,
        "y": 20,
        "w": 23,
        "h": 41
      },
      "sourceSize": {
        "w": 64,
        "h": 64
      },
      "pivot": {
        "x": 0.5,
        "y": 0.5
      }
    },
    "Orc-Attack-Up-0.png": {
      "frame": {
        "x": 452,
        "y": 482,
        "w": 30,
        "h": 41
      },
      "rotated": false,
      "trimmed": true,
      "spriteSourceSize": {
        "x": 17,
        "y": 21,
        "w": 30,
        "h": 41
      },
      "sourceSize": {
        "w": 64,
        "h": 64
      },
      "pivot": {
        "x": 0.5,
        "y": 0.5
      }
    },
    "Orc-Walk-Left-2.png": {
      "frame": {
        "x": 194,
        "y": 484,
        "w": 23,
        "h": 41
      },
      "rotated": false,
      "trimmed": true,
      "spriteSourceSize": {
        "x": 20,
        "y": 20,
        "w": 23,
        "h": 41
      },
      "sourceSize": {
        "w": 64,
        "h": 64
      },
      "pivot": {
        "x": 0.5,
        "y": 0.5
      }
    },
    "Orc-Dead-Down-2.png": {
      "frame": {
        "x": 219,
        "y": 480,
        "w": 30,
        "h": 40
      },
      "rotated": false,
      "trimmed": true,
      "spriteSourceSize": {
        "x": 19,
        "y": 24,
        "w": 30,
        "h": 40
      },
      "sourceSize": {
        "w": 64,
        "h": 64
      },
      "pivot": {
        "x": 0.5,
        "y": 0.5
      }
    },
    "Orc-Attack-Up-1.png": {
      "frame": {
        "x": 272,
        "y": 456,
        "w": 26,
        "h": 40
      },
      "rotated": false,
      "trimmed": true,
      "spriteSourceSize": {
        "x": 19,
        "y": 23,
        "w": 26,
        "h": 40
      },
      "sourceSize": {
        "w": 64,
        "h": 64
      },
      "pivot": {
        "x": 0.5,
        "y": 0.5
      }
    },
    "Orc-Attack-Up-2.png": {
      "frame": {
        "x": 487,
        "y": 1,
        "w": 25,
        "h": 40
      },
      "rotated": false,
      "trimmed": true,
      "spriteSourceSize": {
        "x": 20,
        "y": 23,
        "w": 25,
        "h": 40
      },
      "sourceSize": {
        "w": 64,
        "h": 64
      },
      "pivot": {
        "x": 0.5,
        "y": 0.5
      }
    },
    "Elven-Dead-Down-3.png": {
      "frame": {
        "x": 485,
        "y": 374,
        "w": 27,
        "h": 38
      },
      "rotated": false,
      "trimmed": true,
      "spriteSourceSize": {
        "x": 20,
        "y": 26,
        "w": 27,
        "h": 38
      },
      "sourceSize": {
        "w": 64,
        "h": 64
      },
      "pivot": {
        "x": 0.5,
        "y": 0.5
      }
    },
    "Elven-Dead-Down-5.png": {
      "frame": {
        "x": 514,
        "y": 1,
        "w": 34,
        "h": 36
      },
      "rotated": false,
      "trimmed": true,
      "spriteSourceSize": {
        "x": 17,
        "y": 28,
        "w": 34,
        "h": 36
      },
      "sourceSize": {
        "w": 64,
        "h": 64
      },
      "pivot": {
        "x": 0.5,
        "y": 0.5
      }
    },
    "Orc-Dead-Down-5.png": {
      "frame": {
        "x": 514,
        "y": 39,
        "w": 34,
        "h": 34
      },
      "rotated": false,
      "trimmed": true,
      "spriteSourceSize": {
        "x": 18,
        "y": 28,
        "w": 34,
        "h": 34
      },
      "sourceSize": {
        "w": 64,
        "h": 64
      },
      "pivot": {
        "x": 0.5,
        "y": 0.5
      }
    },
    "Orc-Dead-Down-3.png": {
      "frame": {
        "x": 481,
        "y": 43,
        "w": 30,
        "h": 33
      },
      "rotated": false,
      "trimmed": true,
      "spriteSourceSize": {
        "x": 19,
        "y": 28,
        "w": 30,
        "h": 33
      },
      "sourceSize": {
        "w": 64,
        "h": 64
      },
      "pivot": {
        "x": 0.5,
        "y": 0.5
      }
    },
    "Elven-Dead-Down-4.png": {
      "frame": {
        "x": 251,
        "y": 499,
        "w": 32,
        "h": 29
      },
      "rotated": false,
      "trimmed": true,
      "spriteSourceSize": {
        "x": 18,
        "y": 32,
        "w": 32,
        "h": 29
      },
      "sourceSize": {
        "w": 64,
        "h": 64
      },
      "pivot": {
        "x": 0.5,
        "y": 0.5
      }
    },
    "Orc-Dead-Down-4.png": {
      "frame": {
        "x": 285,
        "y": 499,
        "w": 31,
        "h": 28
      },
      "rotated": false,
      "trimmed": true,
      "spriteSourceSize": {
        "x": 19,
        "y": 33,
        "w": 31,
        "h": 28
      },
      "sourceSize": {
        "w": 64,
        "h": 64
      },
      "pivot": {
        "x": 0.5,
        "y": 0.5
      }
    },
    "Arrow-Left.png": {
      "frame": {
        "x": 514,
        "y": 75,
        "w": 31,
        "h": 4
      },
      "rotated": false,
      "trimmed": true,
      "spriteSourceSize": {
        "x": 11,
        "y": 30,
        "w": 31,
        "h": 4
      },
      "sourceSize": {
        "w": 64,
        "h": 64
      },
      "pivot": {
        "x": 0.5,
        "y": 0.5
      }
    },
    "Arrow-Up.png": {
      "frame": {
        "x": 300,
        "y": 410,
        "w": 4,
        "h": 31
      },
      "rotated": false,
      "trimmed": true,
      "spriteSourceSize": {
        "x": 30,
        "y": 15,
        "w": 4,
        "h": 31
      },
      "sourceSize": {
        "w": 64,
        "h": 64
      },
      "pivot": {
        "x": 0.5,
        "y": 0.5
      }
    },
    "Arrow-Right.png": {
      "frame": {
        "x": 481,
        "y": 78,
        "w": 31,
        "h": 4
      },
      "rotated": false,
      "trimmed": true,
      "spriteSourceSize": {
        "x": 18,
        "y": 30,
        "w": 31,
        "h": 4
      },
      "sourceSize": {
        "w": 64,
        "h": 64
      },
      "pivot": {
        "x": 0.5,
        "y": 0.5
      }
    },
    "Arrow-Down.png": {
      "frame": {
        "x": 206,
        "y": 57,
        "w": 4,
        "h": 31
      },
      "rotated": false,
      "trimmed": true,
      "spriteSourceSize": {
        "x": 33,
        "y": 17,
        "w": 4,
        "h": 31
      },
      "sourceSize": {
        "w": 64,
        "h": 64
      },
      "pivot": {
        "x": 0.5,
        "y": 0.5
      }
    }
  },
  "animations": {
    "Elven-Attack-Up": [
      "Elven-Attack-Up-00.png",
      "Elven-Attack-Up-01.png",
      "Elven-Attack-Up-02.png",
      "Elven-Attack-Up-03.png",
      "Elven-Attack-Up-04.png",
      "Elven-Attack-Up-05.png",
      "Elven-Attack-Up-06.png",
      "Elven-Attack-Up-07.png",
      "Elven-Attack-Up-08.png",
      "Elven-Attack-Up-09.png",
      "Elven-Attack-Up-10.png"
    ],
    "Elven-Attack-Down": [
      "Elven-Attack-Down-00.png",
      "Elven-Attack-Down-01.png",
      "Elven-Attack-Down-02.png",
      "Elven-Attack-Down-03.png",
      "Elven-Attack-Down-04.png",
      "Elven-Attack-Down-05.png",
      "Elven-Attack-Down-06.png",
      "Elven-Attack-Down-07.png",
      "Elven-Attack-Down-08.png",
      "Elven-Attack-Down-09.png",
      "Elven-Attack-Down-10.png"
    ],
    "Elven-Attack-Left": [
      "Elven-Attack-Left-00.png",
      "Elven-Attack-Left-01.png",
      "Elven-Attack-Left-02.png",
      "Elven-Attack-Left-03.png",
      "Elven-Attack-Left-04.png",
      "Elven-Attack-Left-05.png",
      "Elven-Attack-Left-06.png",
      "Elven-Attack-Left-07.png",
      "Elven-Attack-Left-08.png",
      "Elven-Attack-Left-09.png",
      "Elven-Attack-Left-10.png"
    ],
    "Elven-Attack-Right": [
      "Elven-Attack-Right-00.png",
      "Elven-Attack-Right-01.png",
      "Elven-Attack-Right-02.png",
      "Elven-Attack-Right-03.png",
      "Elven-Attack-Right-04.png",
      "Elven-Attack-Right-05.png",
      "Elven-Attack-Right-06.png",
      "Elven-Attack-Right-07.png",
      "Elven-Attack-Right-08.png",
      "Elven-Attack-Right-09.png",
      "Elven-Attack-Right-10.png"
    ],
    "Elven-Walk-Left": [
      "Elven-Walk-Left-0.png",
      "Elven-Walk-Left-1.png",
      "Elven-Walk-Left-2.png",
      "Elven-Walk-Left-3.png",
      "Elven-Walk-Left-4.png",
      "Elven-Walk-Left-5.png",
      "Elven-Walk-Left-6.png",
      "Elven-Walk-Left-7.png",
      "Elven-Walk-Left-8.png"
    ],
    "Elven-Walk-Right": [
      "Elven-Walk-Right-0.png",
      "Elven-Walk-Right-1.png",
      "Elven-Walk-Right-2.png",
      "Elven-Walk-Right-3.png",
      "Elven-Walk-Right-4.png",
      "Elven-Walk-Right-5.png",
      "Elven-Walk-Right-6.png",
      "Elven-Walk-Right-7.png",
      "Elven-Walk-Right-8.png"
    ],
    "Elven-Walk-Up": [
      "Elven-Walk-Up-0.png",
      "Elven-Walk-Up-1.png",
      "Elven-Walk-Up-2.png",
      "Elven-Walk-Up-3.png",
      "Elven-Walk-Up-4.png",
      "Elven-Walk-Up-5.png",
      "Elven-Walk-Up-6.png",
      "Elven-Walk-Up-7.png",
      "Elven-Walk-Up-8.png"
    ],
    "Elven-Walk-Down": [
      "Elven-Walk-Down-0.png",
      "Elven-Walk-Down-1.png",
      "Elven-Walk-Down-2.png",
      "Elven-Walk-Down-3.png",
      "Elven-Walk-Down-4.png",
      "Elven-Walk-Down-5.png",
      "Elven-Walk-Down-6.png",
      "Elven-Walk-Down-7.png",
      "Elven-Walk-Down-8.png"
    ],
    "Elven-Dead-Down": [
      "Elven-Dead-Down-0.png",
      "Elven-Dead-Down-1.png",
      "Elven-Dead-Down-2.png",
      "Elven-Dead-Down-3.png",
      "Elven-Dead-Down-4.png",
      "Elven-Dead-Down-5.png"
    ],
    "Orc-Attack-Up": [
      "Orc-Attack-Up-0.png",
      "Orc-Attack-Up-1.png",
      "Orc-Attack-Up-2.png",
      "Orc-Attack-Up-3.png",
      "Orc-Attack-Up-4.png",
      "Orc-Attack-Up-5.png"
    ],
    "Orc-Attack-Down": [
      "Orc-Attack-Down-0.png",
      "Orc-Attack-Down-1.png",
      "Orc-Attack-Down-2.png",
      "Orc-Attack-Down-3.png",
      "Orc-Attack-Down-4.png",
      "Orc-Attack-Down-5.png"
    ],
    "Orc-Attack-Left": [
      "Orc-Attack-Left-0.png",
      "Orc-Attack-Left-1.png",
      "Orc-Attack-Left-2.png",
      "Orc-Attack-Left-3.png",
      "Orc-Attack-Left-4.png",
      "Orc-Attack-Left-5.png"
    ],
    "Orc-Attack-Right": [
      "Orc-Attack-Right-0.png",
      "Orc-Attack-Right-1.png",
      "Orc-Attack-Right-2.png",
      "Orc-Attack-Right-3.png",
      "Orc-Attack-Right-4.png",
      "Orc-Attack-Right-5.png"
    ],
    "Orc-Walk-Left": [
      "Orc-Walk-Left-0.png",
      "Orc-Walk-Left-1.png",
      "Orc-Walk-Left-2.png",
      "Orc-Walk-Left-3.png",
      "Orc-Walk-Left-4.png",
      "Orc-Walk-Left-5.png",
      "Orc-Walk-Left-6.png",
      "Orc-Walk-Left-7.png",
      "Orc-Walk-Left-8.png"
    ],
    "Orc-Walk-Right": [
      "Orc-Walk-Right-0.png",
      "Orc-Walk-Right-1.png",
      "Orc-Walk-Right-2.png",
      "Orc-Walk-Right-3.png",
      "Orc-Walk-Right-4.png",
      "Orc-Walk-Right-5.png",
      "Orc-Walk-Right-6.png",
      "Orc-Walk-Right-7.png",
      "Orc-Walk-Right-8.png"
    ],
    "Orc-Walk-Up": [
      "Orc-Walk-Up-0.png",
      "Orc-Walk-Up-1.png",
      "Orc-Walk-Up-2.png",
      "Orc-Walk-Up-3.png",
      "Orc-Walk-Up-4.png",
      "Orc-Walk-Up-5.png",
      "Orc-Walk-Up-6.png",
      "Orc-Walk-Up-7.png",
      "Orc-Walk-Up-8.png"
    ],
    "Orc-Walk-Down": [
      "Orc-Walk-Down-0.png",
      "Orc-Walk-Down-1.png",
      "Orc-Walk-Down-2.png",
      "Orc-Walk-Down-3.png",
      "Orc-Walk-Down-4.png",
      "Orc-Walk-Down-5.png",
      "Orc-Walk-Down-6.png",
      "Orc-Walk-Down-7.png",
      "Orc-Walk-Down-8.png"
    ],
    "Orc-Dead-Down": [
      "Orc-Dead-Down-0.png",
      "Orc-Dead-Down-1.png",
      "Orc-Dead-Down-2.png",
      "Orc-Dead-Down-3.png",
      "Orc-Dead-Down-4.png",
      "Orc-Dead-Down-5.png"
    ]
  },
  "meta": {
    "app": "http://free-tex-packer.com",
    "version": "0.6.7",
    "image": "spritesheet.png",
    "format": "RGBA8888",
    "size": {
      "w": 549,
      "h": 529
    },
    "scale": 1
  }
}